Metadata-Version: 1.1
Name: cdstools
Version: 0.0.1
Summary: Tools designed for use with CDS data
Home-page: https://github.com/732jhy
Author: Justin Yu
Author-email: 732jhy@gmail.com
License: MIT
Keywords: Credit Default Swap
Platform: UNKNOWN
Classifier: Development Status :: 5 - Production/Stable
Classifier: Intended Audience :: Financial and Insurance Industry
Classifier: Operating System :: Microsoft :: Windows :: Windows 10
Classifier: License :: OSI Approved :: MIT License
Classifier: Programming Language :: Python :: 3
